modules/__init__.py
modules/ai_analyzer.py
modules/big_data.py
modules/comprehensive_analyzer.py
modules/data_flow_manager.py
modules/data_interface.py
modules/global_data.py
modules/platform_integration.py
modules/smart_decision.py
super_job_wizard-2.0.0.dist-info/LICENSE
super_job_wizard-2.0.0.dist-info/METADATA
super_job_wizard-2.0.0.dist-info/WHEEL
super_job_wizard-2.0.0.dist-info/entry_points.txt
super_job_wizard-2.0.0.dist-info/top_level.txt
super_job_wizard-2.0.0.dist-info/RECORD
