Metadata-Version: 2.1
Name: super-job-wizard
Version: 2.0.0
Summary: AI驱动的超级求职助手 - 集成全球化数据分析、智能决策支持、大数据洞察、平台集成和AI分析的终极求职工具
Home-page: https://github.com/yourusername/super-job-wizard
Author: Super Job Wizard Team
Author-email: support@super-job-wizard.com
Project-URL: Bug Reports, https://github.com/yourusername/super-job-wizard/issues
Project-URL: Source, https://github.com/yourusername/super-job-wizard
Project-URL: Documentation, https://github.com/yourusername/super-job-wizard#readme
Keywords: job search,career planning,AI assistant,MCP,salary analysis,job wizard
Classifier: Development Status :: 5 - Production/Stable
Classifier: Intended Audience :: Developers
Classifier: Intended Audience :: End Users/Desktop
Classifier: License :: OSI Approved :: MIT License
Classifier: Operating System :: OS Independent
Classifier: Programming Language :: Python :: 3
Classifier: Programming Language :: Python :: 3.8
Classifier: Programming Language :: Python :: 3.9
Classifier: Programming Language :: Python :: 3.10
Classifier: Programming Language :: Python :: 3.11
Classifier: Programming Language :: Python :: 3.12
Classifier: Programming Language :: Python :: 3.13
Classifier: Topic :: Office/Business :: Financial
Classifier: Topic :: Scientific/Engineering :: Artificial Intelligence
Classifier: Topic :: Software Development :: Libraries :: Python Modules
Classifier: Topic :: Utilities
Requires-Python: >=3.8
License-File: LICENSE
Requires-Dist: mcp >=1.0.0
Requires-Dist: fastmcp >=0.1.0
Requires-Dist: pydantic >=2.0.0
Requires-Dist: requests >=2.28.0
Requires-Dist: jsonschema >=4.0.0
Requires-Dist: python-dateutil >=2.8.0
Requires-Dist: colorama >=0.4.0
Requires-Dist: typing-extensions >=4.0.0
